ConfigSpace/__authors__.py
ConfigSpace/__init__.py
ConfigSpace/__version__.py
ConfigSpace/_condition_tree.py
ConfigSpace/c_util.py
ConfigSpace/conditions.py
ConfigSpace/configuration.py
ConfigSpace/configuration_space.py
ConfigSpace/exceptions.py
ConfigSpace/forbidden.py
ConfigSpace/functional.py
ConfigSpace/py.typed
ConfigSpace/types.py
ConfigSpace/util.py
ConfigSpace/api/__init__.py
ConfigSpace/api/distributions.py
ConfigSpace/api/types/__init__.py
ConfigSpace/api/types/categorical.py
ConfigSpace/api/types/float.py
ConfigSpace/api/types/integer.py
ConfigSpace/hyperparameters/__init__.py
ConfigSpace/hyperparameters/beta_float.py
ConfigSpace/hyperparameters/beta_integer.py
ConfigSpace/hyperparameters/categorical.py
ConfigSpace/hyperparameters/constant.py
ConfigSpace/hyperparameters/distributions.py
ConfigSpace/hyperparameters/float_hyperparameter.py
ConfigSpace/hyperparameters/hp_components.py
ConfigSpace/hyperparameters/hyperparameter.py
ConfigSpace/hyperparameters/integer_hyperparameter.py
ConfigSpace/hyperparameters/normal_float.py
ConfigSpace/hyperparameters/normal_integer.py
ConfigSpace/hyperparameters/numerical_hyperparameter.py
ConfigSpace/hyperparameters/ordinal.py
ConfigSpace/hyperparameters/uniform_float.py
ConfigSpace/hyperparameters/uniform_integer.py
ConfigSpace/read_and_write/__init__.py
ConfigSpace/read_and_write/dictionary.py
ConfigSpace/read_and_write/json.py
ConfigSpace/read_and_write/pcs.py
ConfigSpace/read_and_write/pcs_new.py
configspace-1.2.1.dist-info/licenses/LICENSE
configspace-1.2.1.dist-info/METADATA
configspace-1.2.1.dist-info/WHEEL
configspace-1.2.1.dist-info/top_level.txt
configspace-1.2.1.dist-info/RECORD
