Metadata-Version: 2.4
Name: ConfigSpace
Version: 1.2.1
Summary: Creation and manipulation of parameter configuration spaces for automated algorithm configuration and hyperparameter tuning. 
Author: Matthias Feurer, Katharina Eggensperger, Syed Mohsin Ali, Christina Hernandez Wunsch, Julien-Charles Levesque, Jost Tobias Springenberg, Philipp Mueller, Marius Lindauer, Jorn Tuyls, Eddie Bergman, Arjun Krishnakumar
Maintainer-email: Matthias Feurer <feurerm@informatik.uni-freiburg.de>, Eddie Bergman <eddiebergmanhs@gmail.com>, Arjun Krishnakumar <arjunkrishnakumarmec@gmail.com>, Thijs Snelleman <snelleman@aim.rwth-aachen.de>
License: # ConfigSpace
Project-URL: homepage, https://github.com/automl/ConfigSpace
Project-URL: documentation, https://automl.github.io/ConfigSpace/main/
Keywords: algorithm,configuration,hyperparameter,optimization,empirical,evaluation,black,box
Classifier: Programming Language :: Python :: 3.9
Classifier: Programming Language :: Python :: 3.10
Classifier: Programming Language :: Python :: 3.11
Classifier: Programming Language :: Python :: 3.12
Classifier: Programming Language :: Python :: 3.13
Classifier: Programming Language :: Python :: 3.14
Classifier: Natural Language :: English
Classifier: Intended Audience :: Developers
Classifier: Intended Audience :: Education
Classifier: Intended Audience :: Science/Research
Classifier: License :: OSI Approved :: BSD License
Classifier: Operating System :: POSIX :: Linux
Classifier: Operating System :: Microsoft :: Windows
Classifier: Operating System :: MacOS
Classifier: Topic :: Scientific/Engineering :: Artificial Intelligence
Classifier: Topic :: Scientific/Engineering
Classifier: Topic :: Software Development
Requires-Python: >=3.9
License-File: LICENSE
Requires-Dist: numpy
Requires-Dist: pyparsing
Requires-Dist: scipy
Requires-Dist: typing_extensions
Requires-Dist: more_itertools
Provides-Extra: dev
Requires-Dist: ConfigSpace[docs,test,tooling]; extra == "dev"
Provides-Extra: test
Requires-Dist: pytest>=7; extra == "test"
Requires-Dist: pytest-cov; extra == "test"
Requires-Dist: pytest_cases; extra == "test"
Provides-Extra: tooling
Requires-Dist: mypy; extra == "tooling"
Requires-Dist: pre-commit; extra == "tooling"
Requires-Dist: ruff; extra == "tooling"
Requires-Dist: types-pyyaml; extra == "tooling"
Provides-Extra: docs
Requires-Dist: mkdocs; extra == "docs"
Requires-Dist: mkdocs-material; extra == "docs"
Requires-Dist: mkdocs-autorefs; extra == "docs"
Requires-Dist: mkdocs-gen-files; extra == "docs"
Requires-Dist: mkdocs-literate-nav; extra == "docs"
Requires-Dist: mkdocs-glightbox; extra == "docs"
Requires-Dist: mkdocstrings[python]; extra == "docs"
Requires-Dist: markdown-exec[ansi]; extra == "docs"
Requires-Dist: mike; extra == "docs"
Requires-Dist: pillow; extra == "docs"
Requires-Dist: cairosvg; extra == "docs"
Requires-Dist: black; extra == "docs"
Dynamic: license-file
